Workbook

Sheet LEÓN
B2: GASTOS MENSUALES — 🦁 LEÓN — CASCO ANTIGUO 72 m² · Alquiler: Precio sin IVA (no indicado en anuncio)
B4: CONCEPTO DE GASTO | C4: Ene | D4: Feb | E4: Mar | F4: Abr | G4: May | H4: Jun | I4: Jul | J4: Ago | K4: Sep | L4: Oct | M4: Nov | N4: Dic | O4: TOTAL AÑO
B5: COSTES FIJOS
B6: Alquiler local | C6: 1250 | D6: 1250 | E6: 1250 | F6: 1250 | G6: 1250 | H6: 1250 | I6: 1250 | J6: 1250 | K6: 1250 | L6: 1250 | M6: 1250 | N6: 1250 | O6: =SUM(C6:N6) -> 15000
B7: Sueldos brutos personal | C7: 3600 | D7: 3600 | E7: 3600 | F7: 3600 | G7: 3600 | H7: 3600 | I7: 3600 | J7: 3600 | K7: 3600 | L7: 3600 | M7: 3600 | N7: 3600 | O7: =SUM(C7:N7) -> 43200
B8: Seguridad Social empresa (~30%) | C8: =C7*0.3 -> 1080 | D8: =D7*0.3 -> 1080 | E8: =E7*0.3 -> 1080 | F8: =F7*0.3 -> 1080 | G8: =G7*0.3 -> 1080 | H8: =H7*0.3 -> 1080 | I8: =I7*0.3 -> 1080 | J8: =J7*0.3 -> 1080 | ... N8: =N7*0.3 -> 1080 | O8: =SUM(C8:N8) -> 12960
B9: Suministros (luz + agua + internet) | C9: 500 | D9: 500 | E9: 500 | F9: 500 | G9: 500 | H9: 500 | I9: 500 | J9: 500 | K9: 500 | L9: 500 | M9: 500 | N9: 500 | O9: =SUM(C9:N9) -> 6000
B10: Seguro multirriesgo (mensualidad) | C10: 100 | D10: 100 | E10: 100 | F10: 100 | G10: 100 | H10: 100 | I10: 100 | J10: 100 | K10: 100 | L10: 100 | M10: 100 | N10: 100 | O10: =SUM(C10:N10) -> 1200
B11: Software ERP / TPV (mensualidad) | C11: 83 | D11: 83 | E11: 83 | F11: 83 | G11: 83 | H11: 83 | I11: 83 | J11: 83 | K11: 83 | L11: 83 | M11: 83 | N11: 83 | O11: =SUM(C11:N11) -> 996
B12: Asesoría / gestoría (parte proporcional) | C12: 75 | D12: 75 | E12: 75 | F12: 75 | G12: 75 | H12: 75 | I12: 75 | J12: 75 | K12: 75 | L12: 75 | M12: 75 | N12: 75 | O12: =SUM(C12:N12) -> 900
B13: Limpieza profesional | C13: 120 | D13: 120 | E13: 120 | F13: 120 | G13: 120 | H13: 120 | I13: 120 | J13: 120 | K13: 120 | L13: 120 | M13: 120 | N13: 120 | O13: =SUM(C13:N13) -> 1440
B14: Mantenimiento preventivo | C14: 67 | D14: 67 | E14: 67 | F14: 67 | G14: 67 | H14: 67 | I14: 67 | J14: 67 | K14: 67 | L14: 67 | M14: 67 | N14: 67 | O14: =SUM(C14:N14) -> 804
B15: COSTES VARIABLES
B16: Reposición stock piezas reparación | C16: 1500 | D16: 1500 | E16: 1500 | F16: 1500 | G16: 1500 | H16: 1500 | I16: 1500 | J16: 1500 | K16: 1500 | L16: 1500 | M16: 1500 | N16: 1500 | O16: =SUM(C16:N16) -> 18000
B17: Reposición stock dispositivos | C17: 2000 | D17: 2000 | E17: 2000 | F17: 2000 | G17: 2000 | H17: 2000 | I17: 2000 | J17: 2000 | K17: 2000 | L17: 2000 | M17: 2000 | N17: 2000 | O17: =SUM(C17:N17) -> 24000
B18: Logística y mensajería | C18: 150 | D18: 150 | E18: 150 | F18: 150 | G18: 150 | H18: 150 | I18: 150 | J18: 150 | K18: 150 | L18: 150 | M18: 150 | N18: 150 | O18: =SUM(C18:N18) -> 1800
B19: Publicidad local (Google/Meta) | C19: 250 | D19: 250 | E19: 250 | F19: 250 | G19: 250 | H19: 250 | I19: 250 | J19: 250 | K19: 250 | L19: 250 | M19: 250 | N19: 250 | O19: =SUM(C19:N19) -> 3000
B20: Consumibles de taller | C20: 50 | D20: 50 | E20: 50 | F20: 50 | G20: 50 | H20: 50 | I20: 50 | J20: 50 | K20: 50 | L20: 50 | M20: 50 | N20: 50 | O20: =SUM(C20:N20) -> 600
B21: Materiales de embalaje | C21: 38 | D21: 38 | E21: 38 | F21: 38 | G21: 38 | H21: 38 | I21: 38 | J21: 38 | K21: 38 | L21: 38 | M21: 38 | N21: 38 | O21: =SUM(C21:N21) -> 456
B22: Gastos financieros / banco | C22: 50 | D22: 50 | E22: 50 | F22: 50 | G22: 50 | H22: 50 | I22: 50 | J22: 50 | K22: 50 | L22: 50 | M22: 50 | N22: 50 | O22: =SUM(C22:N22) -> 600
B23: Otros gastos operativos | C23: 75 | D23: 75 | E23: 75 | F23: 75 | G23: 75 | H23: 75 | I23: 75 | J23: 75 | K23: 75 | L23: 75 | M23: 75 | N23: 75 | O23: =SUM(C23:N23) -> 900
B24: ✅ TOTAL GASTOS MENSUALES | C24: =SUM(C5:C23) -> 10988 | D24: =SUM(D5:D23) -> 10988 | E24: =SUM(E5:E23) -> 10988 | F24: =SUM(F5:F23) -> 10988 | G24: =SUM(G5:G23) -> 10988 | H24: =SUM(H5:H23) -> 10988 | I24: =SUM(I5:I23) -> 10988 | J24: =SUM(J5:J23) -> 10988 | ... O24: =SUM(O5:O23) -> 131856
B26: 👥 DETALLE DE PERSONAL
B27: Puesto | C27: Neto/mes (aprox.) | D27: Bruto/mes | E27: SS empresa (30%) | F27: Coste total/mes
B28: Técnico reparaciones | C28: 1443 | D28: 1850 | E28: =D28*0.3 -> 555 | F28: =D28+E28 -> 2405
B29: Vendedor/a | C29: 1365 | D29: 1750 | E29: =D29*0.3 -> 525 | F29: =D29+E29 -> 2275
B30: Total coste personal/mes | C30: =SUM(C28:C29) -> 2808 | D30: =SUM(D28:D29) -> 3600 | E30: =SUM(E28:E29) -> 1080 | F30: =SUM(F28:F29) -> 4680

Sheet BURGOS
B2: GASTOS MENSUALES — 🏰 BURGOS — CASCO ANTIGUO 110 m² · Alquiler: ⚠️ 1.300 € + IVA 21% = 1.573 € real
B4: CONCEPTO DE GASTO | C4: Ene | D4: Feb | E4: Mar | F4: Abr | G4: May | H4: Jun | I4: Jul | J4: Ago | K4: Sep | L4: Oct | M4: Nov | N4: Dic | O4: TOTAL AÑO
B5: COSTES FIJOS
B6: Alquiler local | C6: 1573 | D6: 1573 | E6: 1573 | F6: 1573 | G6: 1573 | H6: 1573 | I6: 1573 | J6: 1573 | K6: 1573 | L6: 1573 | M6: 1573 | N6: 1573 | O6: =SUM(C6:N6) -> 18876
B7: Sueldos brutos personal | C7: 3600 | D7: 3600 | E7: 3600 | F7: 3600 | G7: 3600 | H7: 3600 | I7: 3600 | J7: 3600 | K7: 3600 | L7: 3600 | M7: 3600 | N7: 3600 | O7: =SUM(C7:N7) -> 43200
B8: Seguridad Social empresa (~30%) | C8: =C7*0.3 -> 1080 | D8: =D7*0.3 -> 1080 | E8: =E7*0.3 -> 1080 | F8: =F7*0.3 -> 1080 | G8: =G7*0.3 -> 1080 | H8: =H7*0.3 -> 1080 | I8: =I7*0.3 -> 1080 | J8: =J7*0.3 -> 1080 | ... N8: =N7*0.3 -> 1080 | O8: =SUM(C8:N8) -> 12960
B9: Suministros (luz + agua + internet) | C9: 500 | D9: 500 | E9: 500 | F9: 500 | G9: 500 | H9: 500 | I9: 500 | J9: 500 | K9: 500 | L9: 500 | M9: 500 | N9: 500 | O9: =SUM(C9:N9) -> 6000
B10: Seguro multirriesgo (mensualidad) | C10: 100 | D10: 100 | E10: 100 | F10: 100 | G10: 100 | H10: 100 | I10: 100 | J10: 100 | K10: 100 | L10: 100 | M10: 100 | N10: 100 | O10: =SUM(C10:N10) -> 1200
B11: Software ERP / TPV (mensualidad) | C11: 83 | D11: 83 | E11: 83 | F11: 83 | G11: 83 | H11: 83 | I11: 83 | J11: 83 | K11: 83 | L11: 83 | M11: 83 | N11: 83 | O11: =SUM(C11:N11) -> 996
B12: Asesoría / gestoría (parte proporcional) | C12: 75 | D12: 75 | E12: 75 | F12: 75 | G12: 75 | H12: 75 | I12: 75 | J12: 75 | K12: 75 | L12: 75 | M12: 75 | N12: 75 | O12: =SUM(C12:N12) -> 900
B13: Limpieza profesional | C13: 120 | D13: 120 | E13: 120 | F13: 120 | G13: 120 | H13: 120 | I13: 120 | J13: 120 | K13: 120 | L13: 120 | M13: 120 | N13: 120 | O13: =SUM(C13:N13) -> 1440
B14: Mantenimiento preventivo | C14: 67 | D14: 67 | E14: 67 | F14: 67 | G14: 67 | H14: 67 | I14: 67 | J14: 67 | K14: 67 | L14: 67 | M14: 67 | N14: 67 | O14: =SUM(C14:N14) -> 804
B15: COSTES VARIABLES
B16: Reposición stock piezas reparación | C16: 1500 | D16: 1500 | E16: 1500 | F16: 1500 | G16: 1500 | H16: 1500 | I16: 1500 | J16: 1500 | K16: 1500 | L16: 1500 | M16: 1500 | N16: 1500 | O16: =SUM(C16:N16) -> 18000
B17: Reposición stock dispositivos | C17: 2000 | D17: 2000 | E17: 2000 | F17: 2000 | G17: 2000 | H17: 2000 | I17: 2000 | J17: 2000 | K17: 2000 | L17: 2000 | M17: 2000 | N17: 2000 | O17: =SUM(C17:N17) -> 24000
B18: Logística y mensajería | C18: 150 | D18: 150 | E18: 150 | F18: 150 | G18: 150 | H18: 150 | I18: 150 | J18: 150 | K18: 150 | L18: 150 | M18: 150 | N18: 150 | O18: =SUM(C18:N18) -> 1800
B19: Publicidad local (Google/Meta) | C19: 250 | D19: 250 | E19: 250 | F19: 250 | G19: 250 | H19: 250 | I19: 250 | J19: 250 | K19: 250 | L19: 250 | M19: 250 | N19: 250 | O19: =SUM(C19:N19) -> 3000
B20: Consumibles de taller | C20: 50 | D20: 50 | E20: 50 | F20: 50 | G20: 50 | H20: 50 | I20: 50 | J20: 50 | K20: 50 | L20: 50 | M20: 50 | N20: 50 | O20: =SUM(C20:N20) -> 600
B21: Materiales de embalaje | C21: 38 | D21: 38 | E21: 38 | F21: 38 | G21: 38 | H21: 38 | I21: 38 | J21: 38 | K21: 38 | L21: 38 | M21: 38 | N21: 38 | O21: =SUM(C21:N21) -> 456
B22: Gastos financieros / banco | C22: 50 | D22: 50 | E22: 50 | F22: 50 | G22: 50 | H22: 50 | I22: 50 | J22: 50 | K22: 50 | L22: 50 | M22: 50 | N22: 50 | O22: =SUM(C22:N22) -> 600
B23: Otros gastos operativos | C23: 75 | D23: 75 | E23: 75 | F23: 75 | G23: 75 | H23: 75 | I23: 75 | J23: 75 | K23: 75 | L23: 75 | M23: 75 | N23: 75 | O23: =SUM(C23:N23) -> 900
B24: ✅ TOTAL GASTOS MENSUALES | C24: =SUM(C5:C23) -> 11311 | D24: =SUM(D5:D23) -> 11311 | E24: =SUM(E5:E23) -> 11311 | F24: =SUM(F5:F23) -> 11311 | G24: =SUM(G5:G23) -> 11311 | H24: =SUM(H5:H23) -> 11311 | I24: =SUM(I5:I23) -> 11311 | J24: =SUM(J5:J23) -> 11311 | ... O24: =SUM(O5:O23) -> 135732
B26: 👥 DETALLE DE PERSONAL
B27: Puesto | C27: Neto/mes (aprox.) | D27: Bruto/mes | E27: SS empresa (30%) | F27: Coste total/mes
B28: Técnico reparaciones | C28: 1443 | D28: 1850 | E28: =D28*0.3 -> 555 | F28: =D28+E28 -> 2405
B29: Vendedor/a | C29: 1365 | D29: 1750 | E29: =D29*0.3 -> 525 | F29: =D29+E29 -> 2275
B30: Total coste personal/mes | C30: =SUM(C28:C29) -> 2808 | D30: =SUM(D28:D29) -> 3600 | E30: =SUM(E28:E29) -> 1080 | F30: =SUM(F28:F29) -> 4680

Sheet VLL CENTRO
B2: GASTOS MENSUALES — 🏙️ VALLADOLID — CENTRO 62 m² · Alquiler: C/ Duque de la Victoria, 3 — zona prime
B4: CONCEPTO DE GASTO | C4: Ene | D4: Feb | E4: Mar | F4: Abr | G4: May | H4: Jun | I4: Jul | J4: Ago | K4: Sep | L4: Oct | M4: Nov | N4: Dic | O4: TOTAL AÑO
B5: COSTES FIJOS
B6: Alquiler local | C6: 950 | D6: 950 | E6: 950 | F6: 950 | G6: 950 | H6: 950 | I6: 950 | J6: 950 | K6: 950 | L6: 950 | M6: 950 | N6: 950 | O6: =SUM(C6:N6) -> 11400
B7: Sueldos brutos personal | C7: 3600 | D7: 3600 | E7: 3600 | F7: 3600 | G7: 3600 | H7: 3600 | I7: 3600 | J7: 3600 | K7: 3600 | L7: 3600 | M7: 3600 | N7: 3600 | O7: =SUM(C7:N7) -> 43200
B8: Seguridad Social empresa (~30%) | C8: =C7*0.3 -> 1080 | D8: =D7*0.3 -> 1080 | E8: =E7*0.3 -> 1080 | F8: =F7*0.3 -> 1080 | G8: =G7*0.3 -> 1080 | H8: =H7*0.3 -> 1080 | I8: =I7*0.3 -> 1080 | J8: =J7*0.3 -> 1080 | ... N8: =N7*0.3 -> 1080 | O8: =SUM(C8:N8) -> 12960
B9: Suministros (luz + agua + internet) | C9: 500 | D9: 500 | E9: 500 | F9: 500 | G9: 500 | H9: 500 | I9: 500 | J9: 500 | K9: 500 | L9: 500 | M9: 500 | N9: 500 | O9: =SUM(C9:N9) -> 6000
B10: Seguro multirriesgo (mensualidad) | C10: 100 | D10: 100 | E10: 100 | F10: 100 | G10: 100 | H10: 100 | I10: 100 | J10: 100 | K10: 100 | L10: 100 | M10: 100 | N10: 100 | O10: =SUM(C10:N10) -> 1200
B11: Software ERP / TPV (mensualidad) | C11: 83 | D11: 83 | E11: 83 | F11: 83 | G11: 83 | H11: 83 | I11: 83 | J11: 83 | K11: 83 | L11: 83 | M11: 83 | N11: 83 | O11: =SUM(C11:N11) -> 996
B12: Asesoría / gestoría (parte proporcional) | C12: 75 | D12: 75 | E12: 75 | F12: 75 | G12: 75 | H12: 75 | I12: 75 | J12: 75 | K12: 75 | L12: 75 | M12: 75 | N12: 75 | O12: =SUM(C12:N12) -> 900
B13: Limpieza profesional | C13: 120 | D13: 120 | E13: 120 | F13: 120 | G13: 120 | H13: 120 | I13: 120 | J13: 120 | K13: 120 | L13: 120 | M13: 120 | N13: 120 | O13: =SUM(C13:N13) -> 1440
B14: Mantenimiento preventivo | C14: 67 | D14: 67 | E14: 67 | F14: 67 | G14: 67 | H14: 67 | I14: 67 | J14: 67 | K14: 67 | L14: 67 | M14: 67 | N14: 67 | O14: =SUM(C14:N14) -> 804
B15: COSTES VARIABLES
B16: Reposición stock piezas reparación | C16: 1500 | D16: 1500 | E16: 1500 | F16: 1500 | G16: 1500 | H16: 1500 | I16: 1500 | J16: 1500 | K16: 1500 | L16: 1500 | M16: 1500 | N16: 1500 | O16: =SUM(C16:N16) -> 18000
B17: Reposición stock dispositivos | C17: 2000 | D17: 2000 | E17: 2000 | F17: 2000 | G17: 2000 | H17: 2000 | I17: 2000 | J17: 2000 | K17: 2000 | L17: 2000 | M17: 2000 | N17: 2000 | O17: =SUM(C17:N17) -> 24000
B18: Logística y mensajería | C18: 150 | D18: 150 | E18: 150 | F18: 150 | G18: 150 | H18: 150 | I18: 150 | J18: 150 | K18: 150 | L18: 150 | M18: 150 | N18: 150 | O18: =SUM(C18:N18) -> 1800
B19: Publicidad local (Google/Meta) | C19: 250 | D19: 250 | E19: 250 | F19: 250 | G19: 250 | H19: 250 | I19: 250 | J19: 250 | K19: 250 | L19: 250 | M19: 250 | N19: 250 | O19: =SUM(C19:N19) -> 3000
B20: Consumibles de taller | C20: 50 | D20: 50 | E20: 50 | F20: 50 | G20: 50 | H20: 50 | I20: 50 | J20: 50 | K20: 50 | L20: 50 | M20: 50 | N20: 50 | O20: =SUM(C20:N20) -> 600
B21: Materiales de embalaje | C21: 38 | D21: 38 | E21: 38 | F21: 38 | G21: 38 | H21: 38 | I21: 38 | J21: 38 | K21: 38 | L21: 38 | M21: 38 | N21: 38 | O21: =SUM(C21:N21) -> 456
B22: Gastos financieros / banco | C22: 50 | D22: 50 | E22: 50 | F22: 50 | G22: 50 | H22: 50 | I22: 50 | J22: 50 | K22: 50 | L22: 50 | M22: 50 | N22: 50 | O22: =SUM(C22:N22) -> 600
B23: Otros gastos operativos | C23: 75 | D23: 75 | E23: 75 | F23: 75 | G23: 75 | H23: 75 | I23: 75 | J23: 75 | K23: 75 | L23: 75 | M23: 75 | N23: 75 | O23: =SUM(C23:N23) -> 900
B24: ✅ TOTAL GASTOS MENSUALES | C24: =SUM(C5:C23) -> 10688 | D24: =SUM(D5:D23) -> 10688 | E24: =SUM(E5:E23) -> 10688 | F24: =SUM(F5:F23) -> 10688 | G24: =SUM(G5:G23) -> 10688 | H24: =SUM(H5:H23) -> 10688 | I24: =SUM(I5:I23) -> 10688 | J24: =SUM(J5:J23) -> 10688 | ... O24: =SUM(O5:O23) -> 128256
B26: 👥 DETALLE DE PERSONAL
B27: Puesto | C27: Neto/mes (aprox.) | D27: Bruto/mes | E27: SS empresa (30%) | F27: Coste total/mes
B28: Técnico reparaciones | C28: 1443 | D28: 1850 | E28: =D28*0.3 -> 555 | F28: =D28+E28 -> 2405
B29: Vendedor/a | C29: 1365 | D29: 1750 | E29: =D29*0.3 -> 525 | F29: =D29+E29 -> 2275
B30: Total coste personal/mes | C30: =SUM(C28:C29) -> 2808 | D30: =SUM(D28:D29) -> 3600 | E30: =SUM(E28:E29) -> 1080 | F30: =SUM(F28:F29) -> 4680

Sheet VLL ZORRILLA
B2: GASTOS MENSUALES — 🌳 VALLADOLID — ZORRILLA 68 m² · Alquiler: Paseo Zorrilla 177, Covaresa — barrio residencial
B4: CONCEPTO DE GASTO | C4: Ene | D4: Feb | E4: Mar | F4: Abr | G4: May | H4: Jun | I4: Jul | J4: Ago | K4: Sep | L4: Oct | M4: Nov | N4: Dic | O4: TOTAL AÑO
B5: COSTES FIJOS
B6: Alquiler local | C6: 650 | D6: 650 | E6: 650 | F6: 650 | G6: 650 | H6: 650 | I6: 650 | J6: 650 | K6: 650 | L6: 650 | M6: 650 | N6: 650 | O6: =SUM(C6:N6) -> 7800
B7: Sueldos brutos personal | C7: 3600 | D7: 3600 | E7: 3600 | F7: 3600 | G7: 3600 | H7: 3600 | I7: 3600 | J7: 3600 | K7: 3600 | L7: 3600 | M7: 3600 | N7: 3600 | O7: =SUM(C7:N7) -> 43200
B8: Seguridad Social empresa (~30%) | C8: =C7*0.3 -> 1080 | D8: =D7*0.3 -> 1080 | E8: =E7*0.3 -> 1080 | F8: =F7*0.3 -> 1080 | G8: =G7*0.3 -> 1080 | H8: =H7*0.3 -> 1080 | I8: =I7*0.3 -> 1080 | J8: =J7*0.3 -> 1080 | ... N8: =N7*0.3 -> 1080 | O8: =SUM(C8:N8) -> 12960
B9: Suministros (luz + agua + internet) | C9: 500 | D9: 500 | E9: 500 | F9: 500 | G9: 500 | H9: 500 | I9: 500 | J9: 500 | K9: 500 | L9: 500 | M9: 500 | N9: 500 | O9: =SUM(C9:N9) -> 6000
B10: Seguro multirriesgo (mensualidad) | C10: 100 | D10: 100 | E10: 100 | F10: 100 | G10: 100 | H10: 100 | I10: 100 | J10: 100 | K10: 100 | L10: 100 | M10: 100 | N10: 100 | O10: =SUM(C10:N10) -> 1200
B11: Software ERP / TPV (mensualidad) | C11: 83 | D11: 83 | E11: 83 | F11: 83 | G11: 83 | H11: 83 | I11: 83 | J11: 83 | K11: 83 | L11: 83 | M11: 83 | N11: 83 | O11: =SUM(C11:N11) -> 996
B12: Asesoría / gestoría (parte proporcional) | C12: 75 | D12: 75 | E12: 75 | F12: 75 | G12: 75 | H12: 75 | I12: 75 | J12: 75 | K12: 75 | L12: 75 | M12: 75 | N12: 75 | O12: =SUM(C12:N12) -> 900
B13: Limpieza profesional | C13: 120 | D13: 120 | E13: 120 | F13: 120 | G13: 120 | H13: 120 | I13: 120 | J13: 120 | K13: 120 | L13: 120 | M13: 120 | N13: 120 | O13: =SUM(C13:N13) -> 1440
B14: Mantenimiento preventivo | C14: 67 | D14: 67 | E14: 67 | F14: 67 | G14: 67 | H14: 67 | I14: 67 | J14: 67 | K14: 67 | L14: 67 | M14: 67 | N14: 67 | O14: =SUM(C14:N14) -> 804
B15: COSTES VARIABLES
B16: Reposición stock piezas reparación | C16: 1500 | D16: 1500 | E16: 1500 | F16: 1500 | G16: 1500 | H16: 1500 | I16: 1500 | J16: 1500 | K16: 1500 | L16: 1500 | M16: 1500 | N16: 1500 | O16: =SUM(C16:N16) -> 18000
B17: Reposición stock dispositivos | C17: 2000 | D17: 2000 | E17: 2000 | F17: 2000 | G17: 2000 | H17: 2000 | I17: 2000 | J17: 2000 | K17: 2000 | L17: 2000 | M17: 2000 | N17: 2000 | O17: =SUM(C17:N17) -> 24000
B18: Logística y mensajería | C18: 150 | D18: 150 | E18: 150 | F18: 150 | G18: 150 | H18: 150 | I18: 150 | J18: 150 | K18: 150 | L18: 150 | M18: 150 | N18: 150 | O18: =SUM(C18:N18) -> 1800
B19: Publicidad local (Google/Meta) | C19: 250 | D19: 250 | E19: 250 | F19: 250 | G19: 250 | H19: 250 | I19: 250 | J19: 250 | K19: 250 | L19: 250 | M19: 250 | N19: 250 | O19: =SUM(C19:N19) -> 3000
B20: Consumibles de taller | C20: 50 | D20: 50 | E20: 50 | F20: 50 | G20: 50 | H20: 50 | I20: 50 | J20: 50 | K20: 50 | L20: 50 | M20: 50 | N20: 50 | O20: =SUM(C20:N20) -> 600
B21: Materiales de embalaje | C21: 38 | D21: 38 | E21: 38 | F21: 38 | G21: 38 | H21: 38 | I21: 38 | J21: 38 | K21: 38 | L21: 38 | M21: 38 | N21: 38 | O21: =SUM(C21:N21) -> 456
B22: Gastos financieros / banco | C22: 50 | D22: 50 | E22: 50 | F22: 50 | G22: 50 | H22: 50 | I22: 50 | J22: 50 | K22: 50 | L22: 50 | M22: 50 | N22: 50 | O22: =SUM(C22:N22) -> 600
B23: Otros gastos operativos | C23: 75 | D23: 75 | E23: 75 | F23: 75 | G23: 75 | H23: 75 | I23: 75 | J23: 75 | K23: 75 | L23: 75 | M23: 75 | N23: 75 | O23: =SUM(C23:N23) -> 900
B24: ✅ TOTAL GASTOS MENSUALES | C24: =SUM(C5:C23) -> 10388 | D24: =SUM(D5:D23) -> 10388 | E24: =SUM(E5:E23) -> 10388 | F24: =SUM(F5:F23) -> 10388 | G24: =SUM(G5:G23) -> 10388 | H24: =SUM(H5:H23) -> 10388 | I24: =SUM(I5:I23) -> 10388 | J24: =SUM(J5:J23) -> 10388 | ... O24: =SUM(O5:O23) -> 124656
B26: 👥 DETALLE DE PERSONAL
B27: Puesto | C27: Neto/mes (aprox.) | D27: Bruto/mes | E27: SS empresa (30%) | F27: Coste total/mes
B28: Técnico reparaciones | C28: 1443 | D28: 1850 | E28: =D28*0.3 -> 555 | F28: =D28+E28 -> 2405
B29: Vendedor/a | C29: 1365 | D29: 1750 | E29: =D29*0.3 -> 525 | F29: =D29+E29 -> 2275
B30: Total coste personal/mes | C30: =SUM(C28:C29) -> 2808 | D30: =SUM(D28:D29) -> 3600 | E30: =SUM(E28:E29) -> 1080 | F30: =SUM(F28:F29) -> 4680

Sheet 📊 Resumen Consolidado
B2: RESUMEN CONSOLIDADO — GASTOS MENSUALES 4 TIENDAS
B4: CONCEPTO | C4: LEÓN | D4: BURGOS | E4: VLL CENTRO | F4: VLL ZORRILLA | G4: TOTAL 4 TIENDAS
B5: COSTES FIJOS
B6: Alquiler local | C6: =LEÓN!C6 -> 1250 | D6: =BURGOS!C6 -> 1573 | E6: ='VLL CENTRO'!C6 -> 950 | F6: ='VLL ZORRILLA'!C6 -> 650 | G6: =SUM(C6:F6) -> 4423
B7: Sueldos brutos personal | C7: =LEÓN!C7 -> 3600 | D7: =BURGOS!C7 -> 3600 | E7: ='VLL CENTRO'!C7 -> 3600 | F7: ='VLL ZORRILLA'!C7 -> 3600 | G7: =SUM(C7:F7) -> 14400
B8: Seguridad Social empresa (~30%) | C8: =LEÓN!C8 -> 1080 | D8: =BURGOS!C8 -> 1080 | E8: ='VLL CENTRO'!C8 -> 1080 | F8: ='VLL ZORRILLA'!C8 -> 1080 | G8: =SUM(C8:F8) -> 4320
B9: Suministros (luz + agua + internet) | C9: =LEÓN!C9 -> 500 | D9: =BURGOS!C9 -> 500 | E9: ='VLL CENTRO'!C9 -> 500 | F9: ='VLL ZORRILLA'!C9 -> 500 | G9: =SUM(C9:F9) -> 2000
B10: Seguro multirriesgo (mensualidad) | C10: =LEÓN!C10 -> 100 | D10: =BURGOS!C10 -> 100 | E10: ='VLL CENTRO'!C10 -> 100 | F10: ='VLL ZORRILLA'!C10 -> 100 | G10: =SUM(C10:F10) -> 400
B11: Software ERP / TPV (mensualidad) | C11: =LEÓN!C11 -> 83 | D11: =BURGOS!C11 -> 83 | E11: ='VLL CENTRO'!C11 -> 83 | F11: ='VLL ZORRILLA'!C11 -> 83 | G11: =SUM(C11:F11) -> 332
B12: Asesoría / gestoría (parte proporcional) | C12: =LEÓN!C12 -> 75 | D12: =BURGOS!C12 -> 75 | E12: ='VLL CENTRO'!C12 -> 75 | F12: ='VLL ZORRILLA'!C12 -> 75 | G12: =SUM(C12:F12) -> 300
B13: Limpieza profesional | C13: =LEÓN!C13 -> 120 | D13: =BURGOS!C13 -> 120 | E13: ='VLL CENTRO'!C13 -> 120 | F13: ='VLL ZORRILLA'!C13 -> 120 | G13: =SUM(C13:F13) -> 480
B14: Mantenimiento preventivo | C14: =LEÓN!C14 -> 67 | D14: =BURGOS!C14 -> 67 | E14: ='VLL CENTRO'!C14 -> 67 | F14: ='VLL ZORRILLA'!C14 -> 67 | G14: =SUM(C14:F14) -> 268
B15: COSTES VARIABLES
B16: Reposición stock piezas reparación | C16: =LEÓN!C16 -> 1500 | D16: =BURGOS!C16 -> 1500 | E16: ='VLL CENTRO'!C16 -> 1500 | F16: ='VLL ZORRILLA'!C16 -> 1500 | G16: =SUM(C16:F16) -> 6000
B17: Reposición stock dispositivos | C17: =LEÓN!C17 -> 2000 | D17: =BURGOS!C17 -> 2000 | E17: ='VLL CENTRO'!C17 -> 2000 | F17: ='VLL ZORRILLA'!C17 -> 2000 | G17: =SUM(C17:F17) -> 8000
B18: Logística y mensajería | C18: =LEÓN!C18 -> 150 | D18: =BURGOS!C18 -> 150 | E18: ='VLL CENTRO'!C18 -> 150 | F18: ='VLL ZORRILLA'!C18 -> 150 | G18: =SUM(C18:F18) -> 600
B19: Publicidad local (Google/Meta) | C19: =LEÓN!C19 -> 250 | D19: =BURGOS!C19 -> 250 | E19: ='VLL CENTRO'!C19 -> 250 | F19: ='VLL ZORRILLA'!C19 -> 250 | G19: =SUM(C19:F19) -> 1000
B20: Consumibles de taller | C20: =LEÓN!C20 -> 50 | D20: =BURGOS!C20 -> 50 | E20: ='VLL CENTRO'!C20 -> 50 | F20: ='VLL ZORRILLA'!C20 -> 50 | G20: =SUM(C20:F20) -> 200
B21: Materiales de embalaje | C21: =LEÓN!C21 -> 38 | D21: =BURGOS!C21 -> 38 | E21: ='VLL CENTRO'!C21 -> 38 | F21: ='VLL ZORRILLA'!C21 -> 38 | G21: =SUM(C21:F21) -> 152
B22: Gastos financieros / banco | C22: =LEÓN!C22 -> 50 | D22: =BURGOS!C22 -> 50 | E22: ='VLL CENTRO'!C22 -> 50 | F22: ='VLL ZORRILLA'!C22 -> 50 | G22: =SUM(C22:F22) -> 200
B23: Otros gastos operativos | C23: =LEÓN!C23 -> 75 | D23: =BURGOS!C23 -> 75 | E23: ='VLL CENTRO'!C23 -> 75 | F23: ='VLL ZORRILLA'!C23 -> 75 | G23: =SUM(C23:F23) -> 300
B24: ✅ TOTAL MENSUAL (4 TIENDAS) | C24: =LEÓN!C24 -> 10988 | D24: =BURGOS!C24 -> 11311 | E24: ='VLL CENTRO'!C24 -> 10688 | F24: ='VLL ZORRILLA'!C24 -> 10388 | G24: =SUM(C24:F24) -> 43375
